pypluggy/__init__.py
pypluggy/mgr.py
pypluggy/static.py
pypluggy-0.0.15.dist-info/LICENSE
pypluggy-0.0.15.dist-info/METADATA
pypluggy-0.0.15.dist-info/WHEEL
pypluggy-0.0.15.dist-info/top_level.txt
pypluggy-0.0.15.dist-info/RECORD
